LICENSE
MANIFEST.in
README.md
VERSION
clt.py
setup.py
wsgi_srv.py
usrv/__init__.py
usrv/app.py
usrv/req.py
usrv/route.py
usrv/secp256k1.py
usrv/wsgi.py
usrv.egg-info/PKG-INFO
usrv.egg-info/SOURCES.txt
usrv.egg-info/dependency_links.txt
usrv.egg-info/entry_points.txt
usrv.egg-info/requires.txt
usrv.egg-info/top_level.txt
usrv/plugins/binance.py
usrv/plugins/pinata.py