Metadata-Version: 2.1
Name: usrv
Version: 0.4.2
Summary: Pure python micro web framework
Home-page: https://moustikitos.github.io/micro-server
Download-URL: https://github.com/Moustikitos/micro-server/archive/master.zip
Author: THOORENS Bruno
Author-email: moustikitos@gmail.com
Maintainer: THOORENS Bruno
Maintainer-email: moustikitos@gmail.com
License: Cpyright 2020 - 2021 THOORENS Bruno
Project-URL: Bug Reports, https://github.com/Moustikitos/micro-server/issues
Project-URL: Funding, https://github.com/Moustikitos/micro-server/?tab=readme-ov-file#support-this-project
Project-URL: Source, https://github.com/Moustikitos/micro-server
Keywords: micro,framework,HTTP
Classifier: Development Status :: 5 - Production/Stable
Classifier: Environment :: Console
Classifier: Environment :: Web Environment
Classifier: Intended Audience :: Developers
Classifier: Intended Audience :: End Users/Desktop
Classifier: License :: OSI Approved :: MIT License
Classifier: Operating System :: OS Independent
Classifier: Programming Language :: Python
Classifier: Programming Language :: Python :: 3
Classifier: Topic :: Security :: Cryptography
Classifier: Topic :: Internet :: WWW/HTTP :: WSGI :: Server
License-File: LICENSE
Requires-Dist: waitress
Requires-Dist: pyaes
